{
	"backtraceGraph" : 
	{
		"commands" : 
		[
			"install"
		],
		"files" : 
		[
			"CMakeLists.txt"
		],
		"nodes" : 
		[
			{
				"file" : 0
			},
			{
				"command" : 0,
				"file" : 0,
				"line" : 28,
				"parent" : 0
			},
			{
				"command" : 0,
				"file" : 0,
				"line" : 34,
				"parent" : 0
			},
			{
				"command" : 0,
				"file" : 0,
				"line" : 36,
				"parent" : 0
			},
			{
				"command" : 0,
				"file" : 0,
				"line" : 42,
				"parent" : 0
			},
			{
				"command" : 0,
				"file" : 0,
				"line" : 45,
				"parent" : 0
			},
			{
				"command" : 0,
				"file" : 0,
				"line" : 50,
				"parent" : 0
			},
			{
				"command" : 0,
				"file" : 0,
				"line" : 63,
				"parent" : 0
			}
		]
	},
	"installers" : 
	[
		{
			"backtrace" : 1,
			"component" : "Unspecified",
			"destination" : ".",
			"paths" : 
			[
				"include"
			],
			"type" : "directory"
		},
		{
			"backtrace" : 2,
			"component" : "Unspecified",
			"destination" : "lib",
			"paths" : 
			[
				"libfixposition_gnss_tf.so"
			],
			"targetId" : "fixposition_gnss_tf::@6890427a1f51a3e7e1df",
			"targetIndex" : 0,
			"type" : "target"
		},
		{
			"backtrace" : 2,
			"component" : "Unspecified",
			"cxxModuleBmiTarget" : 
			{
				"id" : "fixposition_gnss_tf::@6890427a1f51a3e7e1df",
				"index" : 0
			},
			"destination" : "lib",
			"type" : "cxxModuleBmi"
		},
		{
			"backtrace" : 3,
			"component" : "Unspecified",
			"destination" : "lib",
			"paths" : 
			[
				"libfixposition_gnss_tf.so"
			],
			"targetId" : "fixposition_gnss_tf::@6890427a1f51a3e7e1df",
			"targetIndex" : 0,
			"type" : "target"
		},
		{
			"backtrace" : 4,
			"component" : "Unspecified",
			"destination" : "lib/cmake/fixposition_gnss_tf",
			"exportName" : "fixposition_gnss_tf-targets",
			"exportTargets" : 
			[
				{
					"id" : "fixposition_gnss_tf::@6890427a1f51a3e7e1df",
					"index" : 0
				}
			],
			"paths" : 
			[
				"CMakeFiles/Export/be12ef38b259877964c434aa2bf595c0/fixposition_gnss_tf-targets.cmake"
			],
			"type" : "export"
		},
		{
			"backtrace" : 5,
			"component" : "Unspecified",
			"destination" : "include",
			"paths" : 
			[
				"include/fixposition_gnss_tf"
			],
			"type" : "directory"
		},
		{
			"backtrace" : 6,
			"component" : "Unspecified",
			"destination" : "share/fixposition_gnss_tf",
			"paths" : 
			[
				"package.xml"
			],
			"type" : "file"
		},
		{
			"backtrace" : 7,
			"component" : "Unspecified",
			"destination" : "lib/cmake/fixposition_gnss_tf",
			"paths" : 
			[
				"/home/rhobtor/PHD/test_j8_hayat/J8/build/fixposition_gnss_tf/fixposition_gnss_tf-config.cmake",
				"/home/rhobtor/PHD/test_j8_hayat/J8/build/fixposition_gnss_tf/fixposition_gnss_tf-config-version.cmake"
			],
			"type" : "file"
		}
	],
	"paths" : 
	{
		"build" : ".",
		"source" : "."
	}
}
